setup.py
hamim_dsnd_probability/Binomialdistribution.py
hamim_dsnd_probability/Gaussiandistribution.py
hamim_dsnd_probability/Generaldistribution.py
hamim_dsnd_probability/__init__.py
hamim_dsnd_probability.egg-info/PKG-INFO
hamim_dsnd_probability.egg-info/SOURCES.txt
hamim_dsnd_probability.egg-info/dependency_links.txt
hamim_dsnd_probability.egg-info/not-zip-safe
hamim_dsnd_probability.egg-info/top_level.txt